tqatest/.env
tqatest/app/__init__.py
tqatest/app/api/__init__.py
tqatest/app/api/routes/api.py
tqatest/app/api/routes/predictor.py
tqatest/app/core/config.py
tqatest/app/core/errors.py
tqatest/app/core/events.py
tqatest/app/core/logging.py
tqatest/app/main.py
tqatest/app/model/prediction.py
tqatest/app/services/__init__.py
tqatest/app/services/predict.py
tqatest/app/services/TrainedModel_c++.ann
tqatest/ml/.env
tqatest/ml/libs/annhub.pyd
tqatest/ml/model/__init__.py
tqatest/ml/model/TrainedModel_c++.ann
tqatest-0.0.33.dist-info/WHEEL
tqatest-0.0.33.dist-info/METADATA
tqatest-0.0.33.dist-info/RECORD
