Metadata-Version: 2.1
Name: tqatest
Version: 0.0.33
Summary: Backend module for testing project
Author: QA
Requires-Python: >=3.7,<4.0
Classifier: Programming Language :: Python :: 3
Classifier: Programming Language :: Python :: 3.7
Classifier: Programming Language :: Python :: 3.8
Classifier: Programming Language :: Python :: 3.9
Requires-Dist: fastapi[testclient] (>=0.68.1,<0.69.0)
Requires-Dist: joblib (>=1.0.1,<2.0.0)
Requires-Dist: loguru (>=0.4.0,<0.5.0)
Requires-Dist: pydantic (>=1.3,<2.0)
Requires-Dist: pytest (>=6.2.4,<7.0.0)
Requires-Dist: requests (>=2.22.0,<3.0.0)
Requires-Dist: uvicorn (>=0.11.1,<0.12.0)
